atsphinx/color_text.py
atsphinx_color_text-0.1.1.dist-info/LICENSE
atsphinx_color_text-0.1.1.dist-info/WHEEL
atsphinx_color_text-0.1.1.dist-info/METADATA
atsphinx_color_text-0.1.1.dist-info/RECORD
