Metadata-Version: 2.1
Name: atsphinx-color-text
Version: 0.1.1
Summary: Text color changer for Sphinx.
Author-email: Kazuya Takei <myself@attakei.net>
Classifier: Development Status :: 3 - Alpha
Classifier: Framework :: Sphinx
Classifier: Framework :: Sphinx :: Extension
Classifier: Intended Audience :: Developers
Classifier: License :: OSI Approved :: Apache Software License
Classifier: Programming Language :: Python :: 3.8
Classifier: Programming Language :: Python :: 3.9
Classifier: Programming Language :: Python :: 3.10
Classifier: Programming Language :: Python :: 3.11
Classifier: Programming Language :: Python :: 3.12
Classifier: Topic :: Documentation :: Sphinx
Requires-Dist: sphinx
Requires-Dist: BeautifulSoup4 ; extra == "test"
Requires-Dist: pytest ==7.* ; extra == "test"
Project-URL: Document, https://atsphinx.github.io/color-text
Project-URL: Home, https://github.com/atsphinx/color-text
Provides-Extra: docs
Provides-Extra: test
